.coveragerc
.gitignore
.pre-commit-config.yaml
LICENCE.txt
MANIFEST.in
Makefile
README.md
benchmark.py
pyproject.toml
pytest.ini
requirements.txt
setup.cfg
setup.py
todo.tasks
.github/workflows/build_book.yml
.github/workflows/ci.yml
.github/workflows/publish.yml
.github/workflows/style.yml
backends.egg-info/PKG-INFO
backends.egg-info/SOURCES.txt
backends.egg-info/dependency_links.txt
backends.egg-info/requires.txt
backends.egg-info/top_level.txt
docs/_config.yml
docs/_toc.yml
docs/api.rst
docs/chapter.md
docs/intro.md
docs/logo.png
docs/references.bib
lab/__init__.py
lab/_version.py
lab/control_flow.py
lab/custom.py
lab/generic.py
lab/linear_algebra.py
lab/random.py
lab/shape.py
lab/shaping.py
lab/types.py
lab/util.py
lab/autograd/__init__.py
lab/autograd/custom.py
lab/autograd/generic.py
lab/autograd/linear_algebra.py
lab/autograd/random.py
lab/autograd/shaping.py
lab/bvn_cdf/bvn_cdf.pyx
lab/bvn_cdf/tvpack.f
lab/bvn_cdf/tvpack.h
lab/jax/__init__.py
lab/jax/custom.py
lab/jax/generic.py
lab/jax/linear_algebra.py
lab/jax/random.py
lab/jax/shaping.py
lab/numpy/__init__.py
lab/numpy/generic.py
lab/numpy/linear_algebra.py
lab/numpy/random.py
lab/numpy/shaping.py
lab/tensorflow/__init__.py
lab/tensorflow/custom.py
lab/tensorflow/generic.py
lab/tensorflow/linear_algebra.py
lab/tensorflow/random.py
lab/tensorflow/shaping.py
lab/torch/__init__.py
lab/torch/custom.py
lab/torch/generic.py
lab/torch/linear_algebra.py
lab/torch/random.py
lab/torch/shaping.py
tests/__init__.py
tests/test_control_flow.py
tests/test_custom.py
tests/test_generic.py
tests/test_linear_algebra.py
tests/test_random.py
tests/test_shape.py
tests/test_shaping.py
tests/test_types.py
tests/test_util.py
tests/util.py