Metadata-Version: 2.1
Name: backends
Version: 1.5.5
Summary: A generic interface for linear algebra backends
Home-page: https://github.com/wesselb/lab
Author: Wessel Bruinsma
Author-email: wessel.p.bruinsma@gmail.com
License: MIT
Requires-Python: >=3.8
License-File: LICENCE.txt
Requires-Dist: numpy>=1.16
Requires-Dist: scipy>=1.3
Requires-Dist: fdm
Requires-Dist: plum-dispatch>=2
Requires-Dist: opt-einsum
